pyro_ops/__init__.py
pyro_ops/analysis_core.py
pyro_ops/data_interface.py
pyro_ops/data_persistence.py
pyro_ops/ground_integration.py
pyro_ops/operations_control.py
pyro_ops-0.1.1.dist-info/licenses/LICENSE
pyro_ops-0.1.1.dist-info/METADATA
pyro_ops-0.1.1.dist-info/WHEEL
pyro_ops-0.1.1.dist-info/top_level.txt
pyro_ops-0.1.1.dist-info/RECORD
